fastapi_boilerplate_cli/__init__.py
fastapi_boilerplate_cli/cli.py
fastapi_boilerplate_cli-0.1.1.dist-info/METADATA
fastapi_boilerplate_cli-0.1.1.dist-info/WHEEL
fastapi_boilerplate_cli-0.1.1.dist-info/entry_points.txt
fastapi_boilerplate_cli-0.1.1.dist-info/licenses/LICENSE
fastapi_boilerplate_cli-0.1.1.dist-info/RECORD
