Metadata-Version: 2.4
Name: fastapi-boilerplate-cli
Version: 0.1.1
Summary: A CLI tool to generate FastAPI project boilerplates
Project-URL: Homepage, https://github.com/onlymy-me/fastapi-boilerplate-cli
Project-URL: Repository, https://github.com/onlymy-me/fastapi-boilerplate-cli.git
Project-URL: Issues, https://github.com/onlymy-me/fastapi_boilerplate_cli
Author-email: Brian Obara <mrobaraabuga@gmail.com>
License-File: LICENSE
Keywords: boilerplate,cli,fastapi,generator,scaffold
Classifier: Development Status :: 3 - Alpha
Classifier: Intended Audience :: Developers
Classifier: License :: OSI Approved :: MIT License
Classifier: Operating System :: OS Independent
Classifier: Programming Language :: Python :: 3
Classifier: Programming Language :: Python :: 3.8
Classifier: Programming Language :: Python :: 3.9
Classifier: Programming Language :: Python :: 3.10
Classifier: Programming Language :: Python :: 3.11
Classifier: Programming Language :: Python :: 3.12
Classifier: Programming Language :: Python :: 3.13
Classifier: Topic :: Software Development :: Code Generators
Requires-Python: >=3.8
